reorder/__init__.py
reorder/client.py
reorder/manager.py
reorder/plugin.py
nose_reorder-0.0.5.dist-info/LICENSE
nose_reorder-0.0.5.dist-info/METADATA
nose_reorder-0.0.5.dist-info/WHEEL
nose_reorder-0.0.5.dist-info/entry_points.txt
nose_reorder-0.0.5.dist-info/top_level.txt
nose_reorder-0.0.5.dist-info/RECORD
