Metadata-Version: 2.1
Name: nose-reorder
Version: 0.0.5
Summary: A nose plugin to reorder tests by likelihood of failure
Home-page: https://github.com/launchableinc/nose-reorder
Author: Launchable team
Author-email: info@launchableinc.com
License: UNKNOWN
Platform: UNKNOWN
Classifier: Development Status :: 3 - Alpha
Classifier: Intended Audience :: Developers
Classifier: License :: OSI Approved :: Apache Software License
Classifier: Programming Language :: Python :: 3
Requires-Dist: nose (>=1.0.0)
Requires-Dist: boto3 (>=1.0.0)
Requires-Dist: requests (>=2.0.0)
